[
  {
    "id": 1,
    "image": "./assets/images/avocado.jpg",
    "clicked": false
  },
  {
    "id": 2,
    "image": "./assets/images/apple.jpg",
    "clicked": false
  },
  {
    "id": 3,
    "image": "./assets/images/berry.jpeg",
    "clicked": false
  },
  {
    "id": 4,
    "image": "./assets/images/cherry.jpg",
    "clicked": false
  },
  {
    "id": 5,
    "image": "./assets/images/festival.jpeg",
    "clicked": false
  },
  {
    "id": 6,
    "image": "./assets/images/fruits.jpg",
    "clicked": false
  },
  {
    "id": 7,
    "image": "./assets/images/grapes.jpeg",
    "clicked": false
  },
  {
    "id": 8,
    "image": "./assets/images/heart.jpg",
    "clicked": false
  },
  {
    "id": 9,
    "image": "./assets/images/ice.jpg",
    "clicked": false
  },
  {
    "id": 10,
    "image": "./assets/images/water.jpeg",
    "clicked": false
  },
  {
    "id": 11,
    "image": "./assets/images/juice.jpeg",
    "clicked": false
  },
  {
    "id": 12,
    "image": "./assets/images/lemon.jpg",
    "clicked": false
  }
]
